setup.py
./Main.py
./PiFunctions.py
./PiParameterLookup.py
./PiTypes.py
./PiTypesMore.py
./__init__.py
./josh.py
PythonForPicam.egg-info/PKG-INFO
PythonForPicam.egg-info/SOURCES.txt
PythonForPicam.egg-info/dependency_links.txt
PythonForPicam.egg-info/not-zip-safe
PythonForPicam.egg-info/requires.txt
PythonForPicam.egg-info/top_level.txt