Metadata-Version: 1.0
Name: PythonForPicam
Version: 0.3
Summary: Setup Tools version of PythonForPicam (Joe Lowney 2013)
Home-page: https://github.com/joshStillerman/PythonForPicam
Author: Joe Lowney,Josh Stillerman
Author-email: jas@psfc.mit.edu
License: UNKNOWN
Keywords: princeton instruments,camera
Platform: Windows
Classifier: Development Status :: 4 - Beta
Classifier: Programming Language :: Python
Classifier: Intended Audience :: Science/Research
Classifier: Environment :: Console
Classifier: Topic :: Scientific/Engineering
